django_tabular_export-1.2.0.dist-info/licenses/AUTHORS.rst
django_tabular_export-1.2.0.dist-info/licenses/LICENSE
tabular_export/__init__.py
tabular_export/admin.py
tabular_export/core.py
tabular_export/models.py
django_tabular_export-1.2.0.dist-info/METADATA
django_tabular_export-1.2.0.dist-info/WHEEL
django_tabular_export-1.2.0.dist-info/top_level.txt
django_tabular_export-1.2.0.dist-info/RECORD
